{
  "created_at": "Mon Mar 03 20:20:35 +0000 2014",
  "id": 440582530937286656,
  "id_str": "440582530937286656",
  "text": "RT @Its_a_Horror: 友達100人できるかなって曲。 「100人で食べたいな　富士山の上でおにぎりを」 1人ハブられてるじゃねーか",
  "source": "<a href=\"http://www.yahoo.co.jp\" rel=\"nofollow\">ふなっしー.com</a>",
  "truncated": false,
  "in_reply_to_status_id": null,
  "in_reply_to_status_id_str": null,
  "in_reply_to_user_id": null,
  "in_reply_to_user_id_str": null,
  "in_reply_to_screen_name": null,
  "user": {
    "id": 2356071348,
    "id_str": "2356071348",
    "name": "〇〇を科学してみたｗ",
    "screen_name": "KaGaKu_x_KuSo",
    "location": "",
    "url": null,
    "description": "科学が止まらない。",
    "protected": false,
    "followers_count": 835,
    "friends_count": 0,
    "listed_count": 2,
    "created_at": "Sat Feb 22 09:17:57 +0000 2014",
    "favourites_count": 0,
    "utc_offset": null,
    "time_zone": null,
    "geo_enabled": false,
    "verified": false,
    "statuses_count": 875,
    "lang": "ja",
    "contributors_enabled": false,
    "is_translator": false,
    "is_translation_enabled": false,
    "profile_background_color": "131516",
    "profile_background_image_url": "http://abs.twimg.com/images/themes/theme14/bg.gif",
    "profile_background_image_url_https": "https://abs.twimg.com/images/themes/theme14/bg.gif",
    "profile_background_tile": true,
    "profile_image_url": "http://pbs.twimg.com/profile_images/437163474397827073/E2_gE_Og_normal.jpeg",
    "profile_image_url_https": "https://pbs.twimg.com/profile_images/437163474397827073/E2_gE_Og_normal.jpeg",
    "profile_banner_url": "https://pbs.twimg.com/profile_banners/2356071348/1393062904",
    "profile_link_color": "009999",
    "profile_sidebar_border_color": "EEEEEE",
    "profile_sidebar_fill_color": "EFEFEF",
    "profile_text_color": "333333",
    "profile_use_background_image": true,
    "default_profile": false,
    "default_profile_image": false,
    "following": null,
    "follow_request_sent": null,
    "notifications": null
  },
  "geo": null,
  "coordinates": null,
  "place": null,
  "contributors": null,
  "retweeted_status": {
    "created_at": "Mon Mar 03 19:45:28 +0000 2014",
    "id": 440573690900541441,
    "id_str": "440573690900541441",
    "text": "友達100人できるかなって曲。 「100人で食べたいな　富士山の上でおにぎりを」 1人ハブられてるじゃねーか",
    "source": "<a href=\"http://www.yahoo.co.jp\" rel=\"nofollow\">ふなっしー.com</a>",
    "truncated": false,
    "in_reply_to_status_id": null,
    "in_reply_to_status_id_str": null,
    "in_reply_to_user_id": null,
    "in_reply_to_user_id_str": null,
    "in_reply_to_screen_name": null,
    "user": {
      "id": 2276268804,
      "id_str": "2276268804",
      "name": "この怖さがおわかりだろうか？",
      "screen_name": "Its_a_Horror",
      "location": "",
      "url": null,
      "description": "意味がわかると怖い話を紹介しています。\n\n時々、息抜きも。",
      "protected": false,
      "followers_count": 10855,
      "friends_count": 0,
      "listed_count": 20,
      "created_at": "Sat Jan 04 15:31:43 +0000 2014",
      "favourites_count": 1,
      "utc_offset": null,
      "time_zone": null,
      "geo_enabled": false,
      "verified": false,
      "statuses_count": 8581,
      "lang": "ja",
      "contributors_enabled": false,
      "is_translator": false,
      "is_translation_enabled": false,
      "profile_background_color": "1A1B1F",
      "profile_background_image_url": "http://abs.twimg.com/images/themes/theme9/bg.gif",
      "profile_background_image_url_https": "https://abs.twimg.com/images/themes/theme9/bg.gif",
      "profile_background_tile": false,
      "profile_image_url": "http://pbs.twimg.com/profile_images/419491584032260096/cBuA_ie__normal.jpeg",
      "profile_image_url_https": "https://pbs.twimg.com/profile_images/419491584032260096/cBuA_ie__normal.jpeg",
      "profile_banner_url": "https://pbs.twimg.com/profile_banners/2276268804/1388849853",
      "profile_link_color": "2FC2EF",
      "profile_sidebar_border_color": "181A1E",
      "profile_sidebar_fill_color": "252429",
      "profile_text_color": "666666",
      "profile_use_background_image": true,
      "default_profile": false,
      "default_profile_image": false,
      "following": null,
      "follow_request_sent": null,
      "notifications": null
    },
    "geo": null,
    "coordinates": null,
    "place": null,
    "contributors": null,
    "retweet_count": 1,
    "favorite_count": 0,
    "entities": {
      "hashtags": [],
      "symbols": [],
      "urls": [],
      "user_mentions": []
    },
    "favorited": false,
    "retweeted": false,
    "lang": "ja"
  },
  "retweet_count": 0,
  "favorite_count": 0,
  "entities": {
    "hashtags": [],
    "symbols": [],
    "urls": [],
    "user_mentions": [
      {
        "screen_name": "Its_a_Horror",
        "name": "この怖さがおわかりだろうか？",
        "id": 2276268804,
        "id_str": "2276268804",
        "indices": [
          3,
          16
        ]
      }
    ]
  },
  "favorited": false,
  "retweeted": false,
  "filter_level": "medium",
  "lang": "ja"
}